{"_type":"export","__export_format":4,"__export_date":"2023-01-08T21:18:53.578Z","__export_source":"insomnia.desktop.app:v2022.7.0","resources":[{"_id":"req_5376719c33de4291a30d7bab475b3b77","parentId":"fld_bdbeda664b054df4a5030c65dcd81a80","modified":1673128271318,"created":1673127784591,"url":"http://localhost:8080/api/pessoas/1/enderecos/1","name":"Deletar endereço","description":"","method":"DELETE","body":{},"parameters":[],"headers":[],"authentication":{},"metaSortKey":-1673127784591,"isPrivate":false,"settingStoreCookies":true,"settingSendCookies":true,"settingDisableRenderRequestBody":false,"settingEncodeUrl":true,"settingRebuildPath":true,"settingFollowRedirects":"global","_type":"request"},{"_id":"fld_bdbeda664b054df4a5030c65dcd81a80","parentId":"wrk_5ae7b18d8f454f0b91b36ec5e6053e9a","modified":1673121594804,"created":1673121585627,"name":"Endereços","description":"","environment":{},"environmentPropertyOrder":null,"metaSortKey":-1673121585627,"_type":"request_group"},{"_id":"wrk_5ae7b18d8f454f0b91b36ec5e6053e9a","parentId":null,"modified":1672890710569,"created":1672890710569,"name":"Teste Técnico","description":"","scope":"collection","_type":"workspace"},{"_id":"req_b699ff112f3a4da2a33927481bcb3e63","parentId":"fld_bdbeda664b054df4a5030c65dcd81a80","modified":1673206530120,"created":1673121596094,"url":"http://localhost:8080/api/pessoas/1/enderecosC","name":"Criar","description":"","method":"POST","body":{"mimeType":"application/json","text":"{\n\t\"numero\": \"872893\",\n\t\"cep\": \"03808-130\",\n\t\"estado\": \"SP\",\n\t\"logradouro\": \"Rua\",\n\t\"cidade\": \"São Paulo\",\n\t\"endereco_principal\":false\n}"},"parameters":[],"headers":[{"name":"Content-Type","value":"application/json"}],"authentication":{},"metaSortKey":-1673121596094,"isPrivate":false,"settingStoreCookies":true,"settingSendCookies":true,"settingDisableRenderRequestBody":false,"settingEncodeUrl":true,"settingRebuildPath":true,"settingFollowRedirects":"global","_type":"request"},{"_id":"req_5d4cce5e21284620ac7c79fa32ae2ecb","parentId":"fld_bdbeda664b054df4a5030c65dcd81a80","modified":1673198265451,"created":1673125463640,"url":"http://localhost:8080/api/pessoas/1/enderecos/1","name":"Editar","description":"","method":"PUT","body":{"mimeType":"application/json","text":"{\n\t\"numero\": \"872893\",\n\t\"cep\": \"03808-190\",\n\t\"estado\": \"SP\",\n\t\"logradouro\": \"Rua Teste\",\n\t\"cidade\": \"São Paulo\",\n\t\"endereco_principal\":true\n}"},"parameters":[],"headers":[{"name":"Content-Type","value":"application/json"}],"authentication":{},"metaSortKey":-1673105175116.5,"isPrivate":false,"settingStoreCookies":true,"settingSendCookies":true,"settingDisableRenderRequestBody":false,"settingEncodeUrl":true,"settingRebuildPath":true,"settingFollowRedirects":"global","_type":"request"},{"_id":"req_fd6984440d434c8b8d107603e191c3a7","parentId":"fld_bdbeda664b054df4a5030c65dcd81a80","modified":1673123073587,"created":1673122982965,"url":"http://localhost:8080/api/pessoas/1/enderecos/4","name":"Recuperar endereço","description":"","method":"GET","body":{},"parameters":[],"headers":[],"authentication":{},"metaSortKey":-1673088754139,"isPrivate":false,"settingStoreCookies":true,"settingSendCookies":true,"settingDisableRenderRequestBody":false,"settingEncodeUrl":true,"settingRebuildPath":true,"settingFollowRedirects":"global","_type":"request"},{"_id":"req_f96a63955c32467c84fe854b7766c1d7","parentId":"fld_bdbeda664b054df4a5030c65dcd81a80","modified":1673202716540,"created":1673124537022,"url":"http://localhost:8080/api/pessoas/1/enderecos?pagina=1","name":"Recuperar tudo","description":"","method":"GET","body":{},"parameters":[],"headers":[],"authentication":{},"metaSortKey":-1673072333161.5,"isPrivate":false,"settingStoreCookies":true,"settingSendCookies":true,"settingDisableRenderRequestBody":false,"settingEncodeUrl":true,"settingRebuildPath":true,"settingFollowRedirects":"global","_type":"request"},{"_id":"req_9815068ead5d4e16ab2754f356e49599","parentId":"fld_bdbeda664b054df4a5030c65dcd81a80","modified":1673198740970,"created":1673128677615,"url":"http://localhost:8080/api/pessoas/1/enderecos/3/endereco_principal","name":"Definir endereço principal","description":"","method":"PATCH","body":{},"parameters":[],"headers":[],"authentication":{},"metaSortKey":-1673064122672.75,"isPrivate":false,"settingStoreCookies":true,"settingSendCookies":true,"settingDisableRenderRequestBody":false,"settingEncodeUrl":true,"settingRebuildPath":true,"settingFollowRedirects":"global","_type":"request"},{"_id":"req_e6561724dd254c98b8046bef17ff62e8","parentId":"fld_7545312ae4a74a7eaaa360ec0db6a894","modified":1673202585260,"created":1673055912184,"url":"http://localhost:8080/api/pessoas?pagina=1","name":"Recuperar tudo","description":"","method":"GET","body":{},"parameters":[],"headers":[],"authentication":{},"metaSortKey":-1673055912184,"isPrivate":false,"settingStoreCookies":true,"settingSendCookies":true,"settingDisableRenderRequestBody":false,"settingEncodeUrl":true,"settingRebuildPath":true,"settingFollowRedirects":"global","_type":"request"},{"_id":"fld_7545312ae4a74a7eaaa360ec0db6a894","parentId":"wrk_5ae7b18d8f454f0b91b36ec5e6053e9a","modified":1672890735765,"created":1672890718379,"name":"Pessoas","description":"","environment":{},"environmentPropertyOrder":null,"metaSortKey":-1672890718379,"_type":"request_group"},{"_id":"req_049a5aeadd3c4c04a880ded1fb06499b","parentId":"fld_7545312ae4a74a7eaaa360ec0db6a894","modified":1673130347604,"created":1673130345104,"url":"http://localhost:8080/api/pessoas/1","name":"Recuperar pessoa","description":"","method":"GET","body":{},"parameters":[],"headers":[],"authentication":{},"metaSortKey":-1672973316042,"isPrivate":false,"settingStoreCookies":true,"settingSendCookies":true,"settingDisableRenderRequestBody":false,"settingEncodeUrl":true,"settingRebuildPath":true,"settingFollowRedirects":"global","_type":"request"},{"_id":"req_f1e34dcc2a2842d8ab9a3a4d366a96be","parentId":"fld_7545312ae4a74a7eaaa360ec0db6a894","modified":1673206718611,"created":1672890719900,"url":"http://localhost:8080/api/pessoas","name":"Criar","description":"","method":"POST","body":{"mimeType":"application/json","text":"{\n\t\"nome\":\"Teste\",\n\t\"data_nascimento\":\"2002-02-22\",\n\t\"numero_principal\": \"123\",\n\t\"cep_principal\": \"03808-130\",\n\t\"estado_principal\": \"SP\",\n\t\"logradouro_principal\": \"Rua\",\n\t\"cidade_principal\": \"São Paulo\"\n}"},"parameters":[],"headers":[{"name":"Content-Type","value":"application/json","id":"pair_8921b7871ae244d4bb0e3f35f4e4374f","disabled":false}],"authentication":{},"metaSortKey":-1672890719900,"isPrivate":false,"settingStoreCookies":true,"settingSendCookies":true,"settingDisableRenderRequestBody":false,"settingEncodeUrl":true,"settingRebuildPath":true,"settingFollowRedirects":"global","_type":"request"},{"_id":"req_980ac16c056a4cb087170c4d58da04bd","parentId":"fld_7545312ae4a74a7eaaa360ec0db6a894","modified":1673194789293,"created":1673052647994,"url":"http://localhost:8080/api/pessoas/1","name":"Editar","description":"","method":"PUT","body":{"mimeType":"application/json","text":"{\n\t\"nome\":\"Teste 3\",\n\t\"data_nascimento\":\"2002-02-22\"\n}"},"parameters":[],"headers":[{"name":"Content-Type","value":"application/json"}],"authentication":{},"metaSortKey":-1672181016478.5,"isPrivate":false,"settingStoreCookies":true,"settingSendCookies":true,"settingDisableRenderRequestBody":false,"settingEncodeUrl":true,"settingRebuildPath":true,"settingFollowRedirects":"global","_type":"request"},{"_id":"req_ff7e0995cf9f4e50a5a7693631033b2f","parentId":"fld_7545312ae4a74a7eaaa360ec0db6a894","modified":1673130393174,"created":1673130385016,"url":"http://localhost:8080/api/pessoas/1","name":"Deletar","description":"","method":"DELETE","body":{},"parameters":[],"headers":[],"authentication":{},"metaSortKey":-1671826164767.75,"isPrivate":false,"settingStoreCookies":true,"settingSendCookies":true,"settingDisableRenderRequestBody":false,"settingEncodeUrl":true,"settingRebuildPath":true,"settingFollowRedirects":"global","_type":"request"},{"_id":"env_c7586706da112f9cdbbe77a27a20ebef2e96fa4c","parentId":"wrk_5ae7b18d8f454f0b91b36ec5e6053e9a","modified":1672890710575,"created":1672890710575,"name":"Base Environment","data":{},"dataPropertyOrder":null,"color":null,"isPrivate":false,"metaSortKey":1672890710575,"_type":"environment"},{"_id":"jar_c7586706da112f9cdbbe77a27a20ebef2e96fa4c","parentId":"wrk_5ae7b18d8f454f0b91b36ec5e6053e9a","modified":1672890710577,"created":1672890710577,"name":"Default Jar","cookies":[],"_type":"cookie_jar"},{"_id":"spc_1c38baf46b6c4da88027edda76043b5b","parentId":"wrk_5ae7b18d8f454f0b91b36ec5e6053e9a","modified":1672890710570,"created":1672890710570,"fileName":"Teste Técnico","contents":"","contentType":"yaml","_type":"api_spec"}]}